tables.py
python_tables-1.1.1.dist-info/LICENSE.md
python_tables-1.1.1.dist-info/METADATA
python_tables-1.1.1.dist-info/WHEEL
python_tables-1.1.1.dist-info/top_level.txt
python_tables-1.1.1.dist-info/RECORD
